pyterrier_ciff/__init__.py
pyterrier_ciff/_ciff_hub_url_resolver.py
pyterrier_ciff/_ciff_pb2.py
pyterrier_ciff/_index.py
pyterrier_ciff/_indexer.py
pyterrier_ciff/_invert.py
pyterrier_ciff/_utils.py
pyterrier_ciff/pt_docs/index.rst
pyterrier_ciff-0.2.1.dist-info/LICENSE
pyterrier_ciff-0.2.1.dist-info/METADATA
pyterrier_ciff-0.2.1.dist-info/WHEEL
pyterrier_ciff-0.2.1.dist-info/entry_points.txt
pyterrier_ciff-0.2.1.dist-info/top_level.txt
pyterrier_ciff-0.2.1.dist-info/RECORD
