Metadata-Version: 2.2
Name: pyterrier-ciff
Version: 0.2.1
Summary: PyTerrier integrations with CIFF
Author-email: Sean MacAvaney <sean.macavaney@glasgow.ac.uk>
Maintainer-email: Sean MacAvaney <sean.macavaney@glasgow.ac.uk>
Project-URL: Repository, https://github.com/seanmacavaney/pyterrier-ciff
Project-URL: Bug Tracker, https://github.com/seanmacavaney/pyterrier-ciff/issues
Classifier: Programming Language :: Python
Classifier: Operating System :: OS Independent
Classifier: Topic :: Text Processing
Classifier: Topic :: Text Processing :: Indexing
Classifier: License :: OSI Approved :: MIT License
Requires-Python: >=3.10
License-File: LICENSE
Requires-Dist: python-terrier
Requires-Dist: protobuf
Requires-Dist: pyterrier-alpha>=0.5.1
